pylint_gitlab/__init__.py
pylint_gitlab/reporter.py
pylint_gitlab/templates/report.html.j2
tests/__init__.py
tests/test_reporter.py
pylint_gitlab-2.0.0.dist-info/LICENSE
pylint_gitlab-2.0.0.dist-info/METADATA
pylint_gitlab-2.0.0.dist-info/WHEEL
pylint_gitlab-2.0.0.dist-info/top_level.txt
pylint_gitlab-2.0.0.dist-info/RECORD
