Metadata-Version: 2.1
Name: pylint-gitlab
Version: 2.0.0
Summary: This project provides pylint formatters for a nice integration with GitLab CI.
Home-page: https://gitlab.com/smueller18/pylint-gitlab
Author: Stephan Müller
Author-email: mail@stephanmueller.eu
License: GPLv3
Project-URL: Documentation, https://gitlab.com/smueller18/pylint-gitlab
Project-URL: Source, https://gitlab.com/smueller18/pylint-gitlab
Project-URL: Tracker, https://gitlab.com/smueller18/pylint-gitlab/issues
Classifier: Programming Language :: Python :: 3
Classifier: License :: OSI Approved :: GNU General Public License v3 (GPLv3)
Classifier: Operating System :: OS Independent
Requires-Python: >=3.7
License-File: LICENSE
Requires-Dist: anybadge
Requires-Dist: astroid
Requires-Dist: dill
Requires-Dist: importlib-metadata
Requires-Dist: isort
Requires-Dist: jinja2
Requires-Dist: markupsafe
Requires-Dist: mccabe
Requires-Dist: packaging
Requires-Dist: platformdirs
Requires-Dist: pylint
Requires-Dist: tomli
Requires-Dist: tomlkit
Requires-Dist: typing-extensions
Requires-Dist: wrapt
Requires-Dist: zipp
